mutatest/__init__.py
mutatest/_devtools.py
mutatest/api.py
mutatest/cache.py
mutatest/cli.py
mutatest/filters.py
mutatest/report.py
mutatest/run.py
mutatest/transformers.py
mutatest/tests/__init__.py
mutatest/tests/all_op_types.py
mutatest/tests/conftest.py
mutatest/tests/test_all_op_types.py
mutatest/tests/test_api.py
mutatest/tests/test_cache.py
mutatest/tests/test_cli.py
mutatest/tests/test_filters.py
mutatest/tests/test_report.py
mutatest/tests/test_run.py
mutatest/tests/test_transformers.py
mutatest-3.1.0.dist-info/LICENSE
mutatest-3.1.0.dist-info/METADATA
mutatest-3.1.0.dist-info/WHEEL
mutatest-3.1.0.dist-info/entry_points.txt
mutatest-3.1.0.dist-info/top_level.txt
mutatest-3.1.0.dist-info/RECORD
