Metadata-Version: 2.1
Name: mutatest
Version: 3.1.0
Summary: Python mutation testing: test your tests!
Home-page: https://github.com/EvanKepner/mutatest
Author: Evan Kepner
Author-email: EvanKepner@users.noreply.github.com
Maintainer: Evan Kepner
License: MIT
Project-URL: Documentation, https://mutatest.readthedocs.io/
Project-URL: Bug Tracker, https://github.com/EvanKepner/mutatest/issues
Project-URL: Source Code, https://github.com/EvanKepner/mutatest
Keywords: mutatest,mutation,testing,test,mutant,mutate,pytest
Platform: UNKNOWN
Classifier: Development Status :: 5 - Production/Stable
Classifier: Intended Audience :: Developers
Classifier: Natural Language :: English
Classifier: Environment :: Console
Classifier: Framework :: Pytest
Classifier: License :: OSI Approved :: MIT License
Classifier: Operating System :: OS Independent
Classifier: Programming Language :: Python :: 3 :: Only
Classifier: Programming Language :: Python :: 3.7
Classifier: Programming Language :: Python :: 3.8
Classifier: Topic :: Utilities
Classifier: Topic :: Software Development :: Libraries
Classifier: Topic :: Software Development :: Libraries :: Python Modules
Classifier: Topic :: Software Development :: Quality Assurance
Classifier: Topic :: Software Development :: Testing
Classifier: Topic :: Software Development :: Testing :: Unit
Requires-Python: >=3.7.0
Provides-Extra: docs
Provides-Extra: tests
Provides-Extra: qa
Provides-Extra: build
Provides-Extra: dev
License-File: LICENSE
